{
  "minecraft:recipes/decorations/crafting_table": {
    "criteria": {
      "unlock_right_away": "2023-12-17 00:20:16 -0500"
    },
    "done": true
  },
  "minecraft:adventure/adventuring_time": {
    "criteria": {
      "minecraft:savanna_plateau": "2023-12-17 00:20:17 -0500"
    },
    "done": false
  },
  "minecraft:nether/obtain_crying_obsidian": {
    "criteria": {
      "crying_obsidian": "2023-12-17 00:22:49 -0500"
    },
    "done": true
  },
  "minecraft:recipes/decorations/respawn_anchor": {
    "criteria": {
      "has_obsidian": "2023-12-17 00:22:49 -0500"
    },
    "done": true
  },
  "minecraft:recipes/tools/flint_and_steel": {
    "criteria": {
      "has_obsidian": "2023-12-17 00:22:51 -0500"
    },
    "done": true
  },
  "minecraft:story/form_obsidian": {
    "criteria": {
      "obsidian": "2023-12-17 00:22:51 -0500"
    },
    "done": true
  },
  "minecraft:recipes/decorations/enchanting_table": {
    "criteria": {
      "has_obsidian": "2023-12-17 00:22:51 -0500"
    },
    "done": true
  },
  "minecraft:recipes/misc/bone_meal": {
    "criteria": {
      "has_bone": "2023-12-17 00:23:59 -0500"
    },
    "done": true
  },
  "minecraft:husbandry/tame_an_animal": {
    "criteria": {
      "tamed_animal": "2023-12-17 00:24:13 -0500"
    },
    "done": true
  },
  "minecraft:recipes/building_blocks/dye_brown_bed": {
    "criteria": {
      "has_needed_dye": "2023-12-17 00:25:40 -0500"
    },
    "done": true
  },
  "minecraft:recipes/building_blocks/dye_brown_carpet": {
    "criteria": {
      "has_needed_dye": "2023-12-17 00:25:40 -0500"
    },
    "done": true
  },
  "minecraft:recipes/decorations/brown_stained_glass_pane_from_glass_pane": {
    "criteria": {
      "has_brown_dye": "2023-12-17 00:25:40 -0500"
    },
    "done": true
  },
  "minecraft:recipes/decorations/brown_candle": {
    "criteria": {
      "has_brown_dye": "2023-12-17 00:25:40 -0500"
    },
    "done": true
  },
  "minecraft:recipes/building_blocks/dye_brown_wool": {
    "criteria": {
      "has_needed_dye": "2023-12-17 00:25:40 -0500"
    },
    "done": true
  },
  "DataVersion": 3465
}